ecuframework/__init__.py
ecuframework/job.py
ecuframework/mcu.py
ecuframework/module.py
ecuframework/util.py
tests/__init__.py
tests/test_simple.py
ecuframework-0.0.4.dist-info/LICENSE
ecuframework-0.0.4.dist-info/METADATA
ecuframework-0.0.4.dist-info/WHEEL
ecuframework-0.0.4.dist-info/top_level.txt
ecuframework-0.0.4.dist-info/RECORD
