Metadata-Version: 2.1
Name: ecuframework
Version: 0.0.4
Summary: Python framework for IoT applications
Home-page: https://github.com/tommasoviciani/ecuframework.git
Author: Tommaso Viciani
Author-email: vicianitommaso17@gmail.com
License: UNKNOWN
Platform: UNKNOWN
Classifier: Programming Language :: Python :: 3
Classifier: License :: OSI Approved :: MIT License
Classifier: Operating System :: OS Independent
Requires-Python: >=3.7
